gdslayout/components.py
gdslayout/init_component.py
gdslayout/layout.py
gdslayout/structure.py
gdslayout/utils.py
gdslayout/visualization.py
gdslayout/device/__init__.py
gdslayout/device/archimedean.py
gdslayout/device/basics.py
gdslayout/device/cavity.py
gdslayout/device/coupler.py
gdslayout/device/mechanics.py
gdslayout/device/phc.py
gdslayout-0.1.3.dist-info/METADATA
gdslayout-0.1.3.dist-info/WHEEL
gdslayout-0.1.3.dist-info/licenses/LICENSE
gdslayout-0.1.3.dist-info/RECORD
