Metadata-Version: 2.4
Name: gdslayout
Version: 0.1.3
Summary: Python library for designing chips' layout.
Project-URL: Homepage, https://github.com/Liu-Wenzheng/gdslayout
Project-URL: Issues, https://github.com/Liu-Wenzheng/gdslayout/issues
Author-email: Liu-Wenzheng <lwz.xqdz@gmail.com>
License: MIT License
License-File: LICENSE
Requires-Python: >=3.13
Requires-Dist: gdsfactory>=9.18
Requires-Dist: matplotlib>=3.10
Requires-Dist: numpy>=2.3
Requires-Dist: pandas>=2.3
Requires-Dist: pyyaml>=6.0
Requires-Dist: rich>=14.1
Requires-Dist: scipy>=1.16
Requires-Dist: tqdm>=4.67
